[
  {
    "strike": 3500,
    "iv": 0.26829037090253594
  },
  {
    "strike": 3600,
    "iv": 0.23877845474604906
  },
  {
    "strike": 3700,
    "iv": 0.20910860805595674
  },
  {
    "strike": 3800,
    "iv": 0.1787568224367562
  },
  {
    "strike": 3900,
    "iv": 0.1478089003072431
  },
  {
    "strike": 4000,
    "iv": 0.1158437447194439
  },
  {
    "strike": 4100,
    "iv": 0.08258751054570558
  },
  {
    "strike": 4200,
    "iv": 0.04750521667693528
  },
  {
    "strike": 4300,
    "iv": 0.01
  }
]