[
  {
    "ts": "2026-01-28T19:38:53.178Z",
    "recommendation": "Hold",
    "strength": 0,
    "size_hint": 0.5,
    "reason": "",
    "last_iv": 0.01561983831908961,
    "ema20": 0.025007813880217132,
    "ema100": 0.031181235092059844
  },
  {
    "ts": "2026-01-28T20:46:28.303Z",
    "recommendation": "Hold",
    "strength": 0,
    "size_hint": 0.5,
    "reason": "",
    "last_iv": 0.019186329447393912,
    "ema20": 0.024453386791376826,
    "ema100": 0.030943712208007054
  },
  {
    "ts": "2026-01-28T21:39:46.147Z",
    "recommendation": "Hold",
    "strength": 0,
    "size_hint": 0.5,
    "reason": "",
    "last_iv": 0.020673267004672265,
    "ema20": 0.02409337538311925,
    "ema100": 0.03074033705546577
  },
  {
    "ts": "2026-01-28T22:43:23.168Z",
    "recommendation": "Hold",
    "strength": 0,
    "size_hint": 0.5,
    "reason": "",
    "last_iv": 0.018208164342942028,
    "ema20": 0.02353287909357856,
    "ema100": 0.030492175219574213
  },
  {
    "ts": "2026-01-28T23:36:10.167Z",
    "recommendation": "Hold",
    "strength": 0,
    "size_hint": 0.5,
    "reason": "",
    "last_iv": 0.015621181238338392,
    "ema20": 0.022779384059746163,
    "ema100": 0.030197700091232908
  },
  {
    "ts": "2026-01-29T02:47:33.143Z",
    "recommendation": "Hold",
    "strength": 0,
    "size_hint": 0.5,
    "reason": "",
    "last_iv": 0.020239168466219606,
    "ema20": 0.022537458765124585,
    "ema100": 0.03000050144519304
  },
  {
    "ts": "2026-01-29T04:46:24.079Z",
    "recommendation": "Long Volatility",
    "strength": 0.6,
    "size_hint": 0.8,
    "reason": "IV at 10th percentile",
    "last_iv": 0.01360325377953757,
    "ema20": 0.021686582099830584,
    "ema100": 0.029675803471615705
  },
  {
    "ts": "2026-01-29T05:55:21.962Z",
    "recommendation": "Long Volatility",
    "strength": 0.6,
    "size_hint": 0.8,
    "reason": "IV at 10th percentile",
    "last_iv": 0.013533992560053484,
    "ema20": 0.020910145000804195,
    "ema100": 0.02935616365158477
  },
  {
    "ts": "2026-01-29T07:02:23.063Z",
    "recommendation": "Hold",
    "strength": 0,
    "size_hint": 0.5,
    "reason": "",
    "last_iv": 0.013882823708106132,
    "ema20": 0.02024087630626152,
    "ema100": 0.029049760880426777
  },
  {
    "ts": "2026-01-29T07:51:05.143Z",
    "recommendation": "Hold",
    "strength": 0,
    "size_hint": 0.5,
    "reason": "",
    "last_iv": 0.017220330939623028,
    "ema20": 0.019953205318962615,
    "ema100": 0.02881551474298512
  },
  {
    "ts": "2026-01-29T08:55:46.438Z",
    "recommendation": "Hold",
    "strength": 0,
    "size_hint": 0.5,
    "reason": "",
    "last_iv": 0.04342022977813502,
    "ema20": 0.022188160029359985,
    "ema100": 0.02910471702090888
  },
  {
    "ts": "2026-01-29T09:55:45.932Z",
    "recommendation": "Hold",
    "strength": 0,
    "size_hint": 0.5,
    "reason": "",
    "last_iv": 0.04116601684682877,
    "ema20": 0.023995574964357013,
    "ema100": 0.029343554641224123
  },
  {
    "ts": "2026-01-29T10:52:47.049Z",
    "recommendation": "Hold",
    "strength": 0,
    "size_hint": 0.5,
    "reason": "",
    "last_iv": 0.040544328846528845,
    "ema20": 0.025571646762659092,
    "ema100": 0.029565352150240056
  },
  {
    "ts": "2026-01-29T11:41:19.714Z",
    "recommendation": "Hold",
    "strength": 0,
    "size_hint": 0.5,
    "reason": "",
    "last_iv": 0.03205398851999595,
    "ema20": 0.02618901264431022,
    "ema100": 0.029614632078354033
  },
  {
    "ts": "2026-01-29T13:21:34.279Z",
    "recommendation": "Hold",
    "strength": 0,
    "size_hint": 0.5,
    "reason": "",
    "last_iv": 0.034690521674203265,
    "ema20": 0.0269986801709667,
    "ema100": 0.029715144743618374
  },
  {
    "ts": "2026-01-29T14:52:42.169Z",
    "recommendation": "Long Volatility",
    "strength": 0.6,
    "size_hint": 0.8,
    "reason": "IV at 10th percentile",
    "last_iv": 0.013004950543015334,
    "ema20": 0.025665944015923713,
    "ema100": 0.02938424980895297
  },
  {
    "ts": "2026-01-29T15:51:56.753Z",
    "recommendation": "Long Volatility",
    "strength": 0.6,
    "size_hint": 0.8,
    "reason": "IV at 10th percentile",
    "last_iv": 0.013321185644225594,
    "ema20": 0.024490252742428654,
    "ema100": 0.029066169330443516
  },
  {
    "ts": "2026-01-29T16:56:06.477Z",
    "recommendation": "Hold",
    "strength": 0,
    "size_hint": 0.5,
    "reason": "",
    "last_iv": 0.024522657263855278,
    "ema20": 0.024493338887326428,
    "ema100": 0.02897619879447147
  },
  {
    "ts": "2026-01-29T17:50:20.900Z",
    "recommendation": "Hold",
    "strength": 0,
    "size_hint": 0.5,
    "reason": "",
    "last_iv": 0.03224238841240004,
    "ema20": 0.025231343604000103,
    "ema100": 0.029040875816608667
  },
  {
    "ts": "2026-01-29T19:01:40.509Z",
    "recommendation": "Short Volatility",
    "strength": 0.6,
    "size_hint": 0.8,
    "reason": "IV at 90th percentile",
    "last_iv": 0.05378855047851717,
    "ema20": 0.02795107759204935,
    "ema100": 0.029530928780210814
  },
  {
    "ts": "2026-01-29T19:38:39.854Z",
    "recommendation": "Long Volatility",
    "strength": 0.6,
    "size_hint": 0.8,
    "reason": "IV at 10th percentile",
    "last_iv": 0.011180512749119104,
    "ema20": 0.026353880940341707,
    "ema100": 0.02916755420533771
  },
  {
    "ts": "2026-01-29T20:44:25.216Z",
    "recommendation": "Short Volatility",
    "strength": 0.6,
    "size_hint": 0.8,
    "reason": "IV at 90th percentile",
    "last_iv": 0.059150329069734435,
    "ema20": 0.02947735219076006,
    "ema100": 0.02976127251948418
  },
  {
    "ts": "2026-01-29T21:38:18.410Z",
    "recommendation": "Hold",
    "strength": 0,
    "size_hint": 0.5,
    "reason": "",
    "last_iv": 0.015675151698888768,
    "ema20": 0.028162856905819936,
    "ema100": 0.029482339433927834
  },
  {
    "ts": "2026-01-29T22:40:44.927Z",
    "recommendation": "Hold",
    "strength": 0,
    "size_hint": 0.5,
    "reason": "",
    "last_iv": 0.016510139108336947,
    "ema20": 0.027053074258440602,
    "ema100": 0.029225464179955737
  },
  {
    "ts": "2026-01-29T23:37:04.148Z",
    "recommendation": "Hold",
    "strength": 0,
    "size_hint": 0.5,
    "reason": "",
    "last_iv": 0.028333603698105024,
    "ema20": 0.027175029443170545,
    "ema100": 0.029207803576354732
  },
  {
    "ts": "2026-01-30T02:48:23.643Z",
    "recommendation": "Hold",
    "strength": 0,
    "size_hint": 0.5,
    "reason": "",
    "last_iv": 0.04126909620545619,
    "ema20": 0.02851732151576918,
    "ema100": 0.02944664105415872
  },
  {
    "ts": "2026-01-30T04:48:40.511Z",
    "recommendation": "Long Volatility",
    "strength": 0.5,
    "size_hint": 0.75,
    "reason": "EMA20 > EMA100 (bullish IV trend)",
    "last_iv": 0.05205627006828105,
    "ema20": 0.03075912613981793,
    "ema100": 0.029894356480180944
  },
  {
    "ts": "2026-01-30T05:57:29.573Z",
    "recommendation": "Hold",
    "strength": 0,
    "size_hint": 0.5,
    "reason": "",
    "last_iv": 0.04967635728798048,
    "ema20": 0.0325607672015477,
    "ema100": 0.030286079268454204
  },
  {
    "ts": "2026-01-30T07:03:31.501Z",
    "recommendation": "Hold",
    "strength": 0,
    "size_hint": 0.5,
    "reason": "",
    "last_iv": 0.029134401824226955,
    "ema20": 0.032234446689421915,
    "ema100": 0.03026327377450911
  },
  {
    "ts": "2026-01-30T07:50:26.397Z",
    "recommendation": "Hold",
    "strength": 0,
    "size_hint": 0.5,
    "reason": "",
    "last_iv": 0.035831546579142136,
    "ema20": 0.03257702763130003,
    "ema100": 0.030373536602323625
  },
  {
    "ts": "2026-01-30T08:54:36.021Z",
    "recommendation": "Hold",
    "strength": 0,
    "size_hint": 0.5,
    "reason": "",
    "last_iv": 0.0367168476049105,
    "ema20": 0.032971296200215314,
    "ema100": 0.03049914672118673
  },
  {
    "ts": "2026-01-30T09:52:38.489Z",
    "recommendation": "Hold",
    "strength": 0,
    "size_hint": 0.5,
    "reason": "",
    "last_iv": 0.022292149026148584,
    "ema20": 0.031954234564589915,
    "ema100": 0.03033663191534439
  },
  {
    "ts": "2026-01-30T10:49:58.739Z",
    "recommendation": "Hold",
    "strength": 0,
    "size_hint": 0.5,
    "reason": "",
    "last_iv": 0.03438905697701724,
    "ema20": 0.03218612241339251,
    "ema100": 0.030416877956169597
  },
  {
    "ts": "2026-01-30T11:37:45.650Z",
    "recommendation": "Hold",
    "strength": 0,
    "size_hint": 0.5,
    "reason": "",
    "last_iv": 0.04023767975192187,
    "ema20": 0.03295293739801436,
    "ema100": 0.03061134927885776
  },
  {
    "ts": "2026-01-30T13:17:57.002Z",
    "recommendation": "Hold",
    "strength": 0,
    "size_hint": 0.5,
    "reason": "",
    "last_iv": 0.039057938114078504,
    "ema20": 0.03353436603763952,
    "ema100": 0.030778608463713615
  },
  {
    "ts": "2026-01-30T14:49:42.534Z",
    "recommendation": "Hold",
    "strength": 0,
    "size_hint": 0.5,
    "reason": "",
    "last_iv": 0.04820649282933401,
    "ema20": 0.03493171144637233,
    "ema100": 0.03112371508481501
  },
  {
    "ts": "2026-01-30T15:48:33.460Z",
    "recommendation": "Hold",
    "strength": 0,
    "size_hint": 0.5,
    "reason": "",
    "last_iv": 0.03603830673405629,
    "ema20": 0.0350371014737708,
    "ema100": 0.031221033731334637
  },
  {
    "ts": "2026-01-30T16:54:55.435Z",
    "recommendation": "Hold",
    "strength": 0,
    "size_hint": 0.5,
    "reason": "",
    "last_iv": 0.03236907478844619,
    "ema20": 0.03478300369421608,
    "ema100": 0.031243767217614075
  },
  {
    "ts": "2026-01-30T17:47:35.705Z",
    "recommendation": "Hold",
    "strength": 0,
    "size_hint": 0.5,
    "reason": "",
    "last_iv": 0.028145872419284575,
    "ema20": 0.03415089595374641,
    "ema100": 0.031182422766162007
  },
  {
    "ts": "2026-01-30T18:58:57.071Z",
    "recommendation": "Hold",
    "strength": 0,
    "size_hint": 0.5,
    "reason": "",
    "last_iv": 0.03851283451163691,
    "ema20": 0.0345663186735455,
    "ema100": 0.03132757943438923
  },
  {
    "ts": "2026-01-30T19:40:09.506Z",
    "recommendation": "Hold",
    "strength": 0,
    "size_hint": 0.5,
    "reason": "",
    "last_iv": 0.048177290287888516,
    "ema20": 0.035862601684435315,
    "ema100": 0.03166123707505258
  },
  {
    "ts": "2026-01-30T20:43:25.289Z",
    "recommendation": "Short Volatility",
    "strength": 0.6,
    "size_hint": 0.8,
    "reason": "IV at 90th percentile",
    "last_iv": 0.05455750860295877,
    "ema20": 0.037643069010008974,
    "ema100": 0.032114628590456655
  },
  {
    "ts": "2026-01-30T21:37:27.729Z",
    "recommendation": "Short Volatility",
    "strength": 0.6,
    "size_hint": 0.8,
    "reason": "IV at 90th percentile",
    "last_iv": 0.06462172872182435,
    "ema20": 0.04021246517303901,
    "ema100": 0.03275833354355304
  },
  {
    "ts": "2026-01-30T22:39:39.485Z",
    "recommendation": "Long Volatility",
    "strength": 0.6,
    "size_hint": 0.8,
    "reason": "IV at 10th percentile",
    "last_iv": 0.012324034344652218,
    "ema20": 0.03755642414176408,
    "ema100": 0.032353693955455995
  },
  {
    "ts": "2026-01-30T23:36:02.140Z",
    "recommendation": "Short Volatility",
    "strength": 0.6,
    "size_hint": 0.8,
    "reason": "IV at 90th percentile",
    "last_iv": 0.06356163069960881,
    "ema20": 0.04003311048060643,
    "ema100": 0.03297167290088476
  },
  {
    "ts": "2026-01-31T02:43:44.986Z",
    "recommendation": "Long Volatility",
    "strength": 0.6,
    "size_hint": 0.8,
    "reason": "IV at 10th percentile",
    "last_iv": 0.012524550674563407,
    "ema20": 0.03741324764193567,
    "ema100": 0.03256677939145266
  },
  {
    "ts": "2026-01-31T04:41:52.206Z",
    "recommendation": "Long Volatility",
    "strength": 0.6,
    "size_hint": 0.8,
    "reason": "IV at 10th percentile",
    "last_iv": 0.012320048933203832,
    "ema20": 0.03502341919348502,
    "ema100": 0.03216585403584377
  },
  {
    "ts": "2026-01-31T05:49:48.887Z",
    "recommendation": "Short Volatility",
    "strength": 0.6,
    "size_hint": 0.8,
    "reason": "IV at 90th percentile",
    "last_iv": 0.06426486166679014,
    "ema20": 0.03780831847665694,
    "ema100": 0.03280147794932786
  },
  {
    "ts": "2026-01-31T06:55:28.891Z",
    "recommendation": "Short Volatility",
    "strength": 0.6,
    "size_hint": 0.8,
    "reason": "IV at 90th percentile",
    "last_iv": 0.061466805184689034,
    "ema20": 0.040061507686945705,
    "ema100": 0.03336910819161224
  },
  {
    "ts": "2026-01-31T07:38:15.641Z",
    "recommendation": "Short Volatility",
    "strength": 0.6,
    "size_hint": 0.8,
    "reason": "IV at 90th percentile",
    "last_iv": 0.05641199121131936,
    "ema20": 0.041618696594028906,
    "ema100": 0.03382540290487377
  }
]