[
  {
    "ts": "2026-03-05T18:16:17.422Z",
    "recommendation": "Hold",
    "strength": 0,
    "size_hint": 0.5,
    "reason": "",
    "last_iv": 0.046886010861821585,
    "ema20": 0.04796976525642081,
    "ema100": 0.046798859569671995
  },
  {
    "ts": "2026-03-05T19:59:11.796Z",
    "recommendation": "Hold",
    "strength": 0,
    "size_hint": 0.5,
    "reason": "",
    "last_iv": 0.052177959645908774,
    "ema20": 0.04837054567446728,
    "ema100": 0.046905376402864796
  },
  {
    "ts": "2026-03-05T20:54:37.202Z",
    "recommendation": "Hold",
    "strength": 0,
    "size_hint": 0.5,
    "reason": "",
    "last_iv": 0.06444530427950527,
    "ema20": 0.04990147506542328,
    "ema100": 0.047252701707352726
  },
  {
    "ts": "2026-03-05T21:47:56.677Z",
    "recommendation": "Hold",
    "strength": 0,
    "size_hint": 0.5,
    "reason": "",
    "last_iv": 0.05878741488676649,
    "ema20": 0.050747755048408345,
    "ema100": 0.047481111869321316
  },
  {
    "ts": "2026-03-05T23:19:02.774Z",
    "recommendation": "Hold",
    "strength": 0,
    "size_hint": 0.5,
    "reason": "",
    "last_iv": 0.05634559769925096,
    "ema20": 0.05128088291991717,
    "ema100": 0.04765664624219121
  },
  {
    "ts": "2026-03-06T02:47:40.298Z",
    "recommendation": "Hold",
    "strength": 0,
    "size_hint": 0.5,
    "reason": "",
    "last_iv": 0.0645015762023977,
    "ema20": 0.05253999656586769,
    "ema100": 0.04799020921170025
  },
  {
    "ts": "2026-03-06T04:49:39.570Z",
    "recommendation": "Hold",
    "strength": 0,
    "size_hint": 0.5,
    "reason": "",
    "last_iv": 0.04584838144102161,
    "ema20": 0.05190269988731092,
    "ema100": 0.0479477967805977
  },
  {
    "ts": "2026-03-06T05:56:13.929Z",
    "recommendation": "Hold",
    "strength": 0,
    "size_hint": 0.5,
    "reason": "",
    "last_iv": 0.041691601914734845,
    "ema20": 0.0509302143661132,
    "ema100": 0.047823911733748926
  },
  {
    "ts": "2026-03-06T07:04:48.954Z",
    "recommendation": "Hold",
    "strength": 0,
    "size_hint": 0.5,
    "reason": "",
    "last_iv": 0.05420374544163908,
    "ema20": 0.05124197923044899,
    "ema100": 0.04795024507449922
  },
  {
    "ts": "2026-03-06T07:50:14.538Z",
    "recommendation": "Hold",
    "strength": 0,
    "size_hint": 0.5,
    "reason": "",
    "last_iv": 0.061303779293790536,
    "ema20": 0.05220024590314819,
    "ema100": 0.04821467149468321
  },
  {
    "ts": "2026-03-06T08:53:12.607Z",
    "recommendation": "Hold",
    "strength": 0,
    "size_hint": 0.5,
    "reason": "",
    "last_iv": 0.0581502270767445,
    "ema20": 0.05276691077682402,
    "ema100": 0.04841141516957551
  },
  {
    "ts": "2026-03-06T09:52:58.375Z",
    "recommendation": "Hold",
    "strength": 0,
    "size_hint": 0.5,
    "reason": "",
    "last_iv": 0.02329876394734633,
    "ema20": 0.049960420602588054,
    "ema100": 0.04791413494735315
  },
  {
    "ts": "2026-03-06T10:51:15.387Z",
    "recommendation": "Hold",
    "strength": 0,
    "size_hint": 0.5,
    "reason": "",
    "last_iv": 0.04177143532641792,
    "ema20": 0.049180517242952804,
    "ema100": 0.04779249733109701
  },
  {
    "ts": "2026-03-06T11:39:07.006Z",
    "recommendation": "Hold",
    "strength": 0,
    "size_hint": 0.5,
    "reason": "",
    "last_iv": 0.04051101338018573,
    "ema20": 0.048354850208403556,
    "ema100": 0.04764830953008886
  },
  {
    "ts": "2026-03-06T13:18:03.088Z",
    "recommendation": "Long Volatility",
    "strength": 1,
    "size_hint": 1,
    "reason": "EMA20 < EMA100 (bearish IV trend); IV at 10th percentile",
    "last_iv": 0.017584015217541996,
    "ema20": 0.04542429449498817,
    "ema100": 0.04705297696944437
  },
  {
    "ts": "2026-03-06T14:51:54.099Z",
    "recommendation": "Hold",
    "strength": 0,
    "size_hint": 0.5,
    "reason": "",
    "last_iv": 0.0631331752912448,
    "ema20": 0.04711085457082214,
    "ema100": 0.04737139673819289
  },
  {
    "ts": "2026-03-06T15:51:08.076Z",
    "recommendation": "Long Volatility",
    "strength": 0.5,
    "size_hint": 0.75,
    "reason": "EMA20 > EMA100 (bullish IV trend)",
    "last_iv": 0.06163248419975025,
    "ema20": 0.04849386691643434,
    "ema100": 0.04765379450970888
  },
  {
    "ts": "2026-03-06T16:56:14.318Z",
    "recommendation": "Hold",
    "strength": 0,
    "size_hint": 0.5,
    "reason": "",
    "last_iv": 0.05353531208479617,
    "ema20": 0.048974004551516424,
    "ema100": 0.047770260204265065
  },
  {
    "ts": "2026-03-06T17:55:09.032Z",
    "recommendation": "Hold",
    "strength": 0,
    "size_hint": 0.5,
    "reason": "",
    "last_iv": 0.042430888758359965,
    "ema20": 0.04835085066645391,
    "ema100": 0.04766453007662338
  },
  {
    "ts": "2026-03-06T19:00:42.240Z",
    "recommendation": "Hold",
    "strength": 0,
    "size_hint": 0.5,
    "reason": "",
    "last_iv": 0.055481773784891025,
    "ema20": 0.049029986201543155,
    "ema100": 0.04781932698173759
  },
  {
    "ts": "2026-03-06T19:42:44.106Z",
    "recommendation": "Hold",
    "strength": 0,
    "size_hint": 0.5,
    "reason": "",
    "last_iv": 0.06749099853061985,
    "ema20": 0.05078817785193141,
    "ema100": 0.0482088650322105
  },
  {
    "ts": "2026-03-06T20:46:00.418Z",
    "recommendation": "Hold",
    "strength": 0,
    "size_hint": 0.5,
    "reason": "",
    "last_iv": 0.06111432655164422,
    "ema20": 0.05177162058523739,
    "ema100": 0.048464418725664635
  },
  {
    "ts": "2026-03-06T21:39:34.229Z",
    "recommendation": "Hold",
    "strength": 0,
    "size_hint": 0.5,
    "reason": "",
    "last_iv": 0.057898172125763425,
    "ema20": 0.05235510168433511,
    "ema100": 0.04865122572368639
  },
  {
    "ts": "2026-03-06T22:42:21.596Z",
    "recommendation": "Hold",
    "strength": 0,
    "size_hint": 0.5,
    "reason": "",
    "last_iv": 0.0648203184703983,
    "ema20": 0.0535422651877697,
    "ema100": 0.04897140577807672
  },
  {
    "ts": "2026-03-06T23:37:13.662Z",
    "recommendation": "Hold",
    "strength": 0,
    "size_hint": 0.5,
    "reason": "",
    "last_iv": 0.06543634047188637,
    "ema20": 0.05467503426244748,
    "ema100": 0.049297444088845226
  },
  {
    "ts": "2026-03-07T02:41:48.907Z",
    "recommendation": "Hold",
    "strength": 0,
    "size_hint": 0.5,
    "reason": "",
    "last_iv": 0.055631274590877314,
    "ema20": 0.05476610476991699,
    "ema100": 0.04942286647502408
  },
  {
    "ts": "2026-03-07T04:38:20.425Z",
    "recommendation": "Hold",
    "strength": 0,
    "size_hint": 0.5,
    "reason": "",
    "last_iv": 0.055257539642718526,
    "ema20": 0.05481290809113618,
    "ema100": 0.04953840455755268
  },
  {
    "ts": "2026-03-07T05:48:00.717Z",
    "recommendation": "Hold",
    "strength": 0,
    "size_hint": 0.5,
    "reason": "",
    "last_iv": 0.059274688826536075,
    "ema20": 0.055237839589745694,
    "ema100": 0.04973120226584938
  },
  {
    "ts": "2026-03-07T06:56:31.658Z",
    "recommendation": "Hold",
    "strength": 0,
    "size_hint": 0.5,
    "reason": "",
    "last_iv": 0.05234281877859242,
    "ema20": 0.05496212332201681,
    "ema100": 0.049782917444319535
  },
  {
    "ts": "2026-03-07T07:38:07.478Z",
    "recommendation": "Hold",
    "strength": 0,
    "size_hint": 0.5,
    "reason": "",
    "last_iv": 0.05785227216161377,
    "ema20": 0.05523737559245461,
    "ema100": 0.04994270664664219
  },
  {
    "ts": "2026-03-07T08:46:32.987Z",
    "recommendation": "Hold",
    "strength": 0,
    "size_hint": 0.5,
    "reason": "",
    "last_iv": 0.06295739429658205,
    "ema20": 0.05597261546903818,
    "ema100": 0.050200423233769706
  },
  {
    "ts": "2026-03-07T09:39:21.350Z",
    "recommendation": "Hold",
    "strength": 0,
    "size_hint": 0.5,
    "reason": "",
    "last_iv": 0.06489242418077522,
    "ema20": 0.05682212106063218,
    "ema100": 0.050491353945591594
  },
  {
    "ts": "2026-03-07T10:36:44.391Z",
    "recommendation": "Hold",
    "strength": 0,
    "size_hint": 0.5,
    "reason": "",
    "last_iv": 0.06518656151755092,
    "ema20": 0.05761873443748159,
    "ema100": 0.050782348154937325
  },
  {
    "ts": "2026-03-07T11:30:50.275Z",
    "recommendation": "Short Volatility",
    "strength": 0.6,
    "size_hint": 0.8,
    "reason": "IV at 90th percentile",
    "last_iv": 0.07015799473520852,
    "ema20": 0.05881294970393177,
    "ema100": 0.051166024324843684
  },
  {
    "ts": "2026-03-07T13:06:50.108Z",
    "recommendation": "Hold",
    "strength": 0,
    "size_hint": 0.5,
    "reason": "",
    "last_iv": 0.06509342108900837,
    "ema20": 0.059411089835843825,
    "ema100": 0.05144181435977764
  },
  {
    "ts": "2026-03-07T14:36:14.382Z",
    "recommendation": "Hold",
    "strength": 0,
    "size_hint": 0.5,
    "reason": "",
    "last_iv": 0.05837701790435472,
    "ema20": 0.059312606794749624,
    "ema100": 0.05157914512303659
  },
  {
    "ts": "2026-03-07T15:34:52.367Z",
    "recommendation": "Hold",
    "strength": 0,
    "size_hint": 0.5,
    "reason": "",
    "last_iv": 0.06301340348910632,
    "ema20": 0.05966506362278359,
    "ema100": 0.05180556608078054
  },
  {
    "ts": "2026-03-07T16:40:36.695Z",
    "recommendation": "Hold",
    "strength": 0,
    "size_hint": 0.5,
    "reason": "",
    "last_iv": 0.06119517531705028,
    "ema20": 0.059810788546047086,
    "ema100": 0.0519914989369443
  },
  {
    "ts": "2026-03-07T17:33:11.036Z",
    "recommendation": "Hold",
    "strength": 0,
    "size_hint": 0.5,
    "reason": "",
    "last_iv": 0.06263604398389733,
    "ema20": 0.06007986049250902,
    "ema100": 0.052202282007180995
  },
  {
    "ts": "2026-03-07T18:49:01.393Z",
    "recommendation": "Hold",
    "strength": 0,
    "size_hint": 0.5,
    "reason": "",
    "last_iv": 0.052505562827647914,
    "ema20": 0.0593584988101413,
    "ema100": 0.05220828756798231
  },
  {
    "ts": "2026-03-07T19:30:43.489Z",
    "recommendation": "Hold",
    "strength": 0,
    "size_hint": 0.5,
    "reason": "",
    "last_iv": 0.03477677819733016,
    "ema20": 0.05701738256130214,
    "ema100": 0.051863109164603065
  },
  {
    "ts": "2026-03-07T20:37:13.605Z",
    "recommendation": "Hold",
    "strength": 0,
    "size_hint": 0.5,
    "reason": "",
    "last_iv": 0.043047288295249425,
    "ema20": 0.055686897393106644,
    "ema100": 0.05168853845431884
  },
  {
    "ts": "2026-03-07T21:32:05.341Z",
    "recommendation": "Hold",
    "strength": 0,
    "size_hint": 0.5,
    "reason": "",
    "last_iv": 0.050139658421888805,
    "ema20": 0.055158588919657324,
    "ema100": 0.05165786756258755
  },
  {
    "ts": "2026-03-07T22:35:50.900Z",
    "recommendation": "Hold",
    "strength": 0,
    "size_hint": 0.5,
    "reason": "",
    "last_iv": 0.04648404499616214,
    "ema20": 0.05433244187932445,
    "ema100": 0.051555415630579124
  },
  {
    "ts": "2026-03-07T23:33:34.478Z",
    "recommendation": "Hold",
    "strength": 0,
    "size_hint": 0.5,
    "reason": "",
    "last_iv": 0.053784392100188226,
    "ema20": 0.05428024666226385,
    "ema100": 0.05159955377849217
  },
  {
    "ts": "2026-03-08T02:53:54.474Z",
    "recommendation": "Short Volatility",
    "strength": 0.6,
    "size_hint": 0.8,
    "reason": "IV at 90th percentile",
    "last_iv": 0.0775068021890886,
    "ema20": 0.0564922995695805,
    "ema100": 0.05211256859850398
  },
  {
    "ts": "2026-03-08T04:51:37.918Z",
    "recommendation": "Short Volatility",
    "strength": 0.6,
    "size_hint": 0.8,
    "reason": "IV at 90th percentile",
    "last_iv": 0.07053455248686652,
    "ema20": 0.057829656990274404,
    "ema100": 0.052477360358669574
  },
  {
    "ts": "2026-03-08T05:54:15.268Z",
    "recommendation": "Long Volatility",
    "strength": 0.6,
    "size_hint": 0.8,
    "reason": "IV at 10th percentile",
    "last_iv": 0.016647734698471646,
    "ema20": 0.053907569152959856,
    "ema100": 0.05176786282084388
  },
  {
    "ts": "2026-03-08T06:58:12.926Z",
    "recommendation": "Short Volatility",
    "strength": 0.6,
    "size_hint": 0.8,
    "reason": "IV at 90th percentile",
    "last_iv": 0.0719554850953146,
    "ema20": 0.055626418290326975,
    "ema100": 0.052167617717368046
  },
  {
    "ts": "2026-03-08T07:39:58.529Z",
    "recommendation": "Hold",
    "strength": 0,
    "size_hint": 0.5,
    "reason": "",
    "last_iv": 0.020700215979129077,
    "ema20": 0.052300113308308124,
    "ema100": 0.0515445008512643
  }
]