[
  {
    "ts": "2025-12-19T21:27:31.573Z",
    "recommendation": "Hold",
    "strength": 0,
    "size_hint": 0.5,
    "reason": "",
    "last_iv": 0.7836426144383485,
    "ema20": 0.7763717205292735,
    "ema100": 0.766490440516933
  },
  {
    "ts": "2025-12-19T22:31:04.926Z",
    "recommendation": "Hold",
    "strength": 0,
    "size_hint": 0.5,
    "reason": "",
    "last_iv": 0.7844309572166053,
    "ema20": 0.7771392668804479,
    "ema100": 0.7668456982733622
  },
  {
    "ts": "2025-12-19T23:28:15.272Z",
    "recommendation": "Hold",
    "strength": 0,
    "size_hint": 0.5,
    "reason": "",
    "last_iv": 0.7828022698496766,
    "ema20": 0.7776786004965648,
    "ema100": 0.7671616699877447
  },
  {
    "ts": "2025-12-20T02:07:46.325Z",
    "recommendation": "Hold",
    "strength": 0,
    "size_hint": 0.5,
    "reason": "",
    "last_iv": 0.7681480809259045,
    "ema20": 0.7767709319660258,
    "ema100": 0.7671812028776093
  },
  {
    "ts": "2025-12-20T03:53:32.427Z",
    "recommendation": "Hold",
    "strength": 0,
    "size_hint": 0.5,
    "reason": "",
    "last_iv": 0.7681981095904072,
    "ema20": 0.7759544726921573,
    "ema100": 0.7672013396441993
  },
  {
    "ts": "2025-12-20T04:36:02.395Z",
    "recommendation": "Hold",
    "strength": 0,
    "size_hint": 0.5,
    "reason": "",
    "last_iv": 0.7681468889898666,
    "ema20": 0.7752108932919392,
    "ema100": 0.7672200633936185
  },
  {
    "ts": "2025-12-20T05:31:25.280Z",
    "recommendation": "Hold",
    "strength": 0,
    "size_hint": 0.5,
    "reason": "",
    "last_iv": 0.7681604041273785,
    "ema20": 0.7745394181334095,
    "ema100": 0.7672386840022077
  },
  {
    "ts": "2025-12-20T06:42:37.344Z",
    "recommendation": "Hold",
    "strength": 0,
    "size_hint": 0.5,
    "reason": "",
    "last_iv": 0.7681547580864615,
    "ema20": 0.7739313552717955,
    "ema100": 0.767256824083084
  },
  {
    "ts": "2025-12-20T07:26:46.127Z",
    "recommendation": "Hold",
    "strength": 0,
    "size_hint": 0.5,
    "reason": "",
    "last_iv": 0.7681303375037006,
    "ema20": 0.7733788773891198,
    "ema100": 0.7672741213785418
  },
  {
    "ts": "2025-12-20T08:36:05.439Z",
    "recommendation": "Hold",
    "strength": 0,
    "size_hint": 0.5,
    "reason": "",
    "last_iv": 0.7696135329911161,
    "ema20": 0.7730202731607385,
    "ema100": 0.767320446360969
  },
  {
    "ts": "2025-12-20T09:28:51.926Z",
    "recommendation": "Hold",
    "strength": 0,
    "size_hint": 0.5,
    "reason": "",
    "last_iv": 0.7690225718515894,
    "ema20": 0.7726395397027244,
    "ema100": 0.7673541518162288
  },
  {
    "ts": "2025-12-20T10:31:14.945Z",
    "recommendation": "Hold",
    "strength": 0,
    "size_hint": 0.5,
    "reason": "",
    "last_iv": 0.7690101643604395,
    "ema20": 0.772293884908221,
    "ema100": 0.7673869441438369
  },
  {
    "ts": "2025-12-20T11:24:03.105Z",
    "recommendation": "Hold",
    "strength": 0,
    "size_hint": 0.5,
    "reason": "",
    "last_iv": 0.7685064361805265,
    "ema20": 0.7719331755055835,
    "ema100": 0.7674091123029793
  },
  {
    "ts": "2025-12-20T12:55:15.696Z",
    "recommendation": "Hold",
    "strength": 0,
    "size_hint": 0.5,
    "reason": "",
    "last_iv": 0.7687914880214636,
    "ema20": 0.7716339671737625,
    "ema100": 0.7674364860795828
  },
  {
    "ts": "2025-12-20T13:33:51.593Z",
    "recommendation": "Hold",
    "strength": 0,
    "size_hint": 0.5,
    "reason": "",
    "last_iv": 0.7683169310808993,
    "ema20": 0.7713180589744423,
    "ema100": 0.7674539206340643
  },
  {
    "ts": "2025-12-20T14:28:11.861Z",
    "recommendation": "Hold",
    "strength": 0,
    "size_hint": 0.5,
    "reason": "",
    "last_iv": 0.7683854650864204,
    "ema20": 0.7710387643184402,
    "ema100": 0.7674723670588635
  },
  {
    "ts": "2025-12-20T15:27:55.243Z",
    "recommendation": "Hold",
    "strength": 0,
    "size_hint": 0.5,
    "reason": "",
    "last_iv": 0.7684663094363215,
    "ema20": 0.7707937686153813,
    "ema100": 0.7674920490861399
  },
  {
    "ts": "2025-12-20T16:34:24.768Z",
    "recommendation": "Hold",
    "strength": 0,
    "size_hint": 0.5,
    "reason": "",
    "last_iv": 0.76846854199061,
    "ema20": 0.7705723184606411,
    "ema100": 0.7675113855792978
  },
  {
    "ts": "2025-12-20T17:26:01.546Z",
    "recommendation": "Hold",
    "strength": 0,
    "size_hint": 0.5,
    "reason": "",
    "last_iv": 0.7687581579687395,
    "ema20": 0.7703995412709362,
    "ema100": 0.7675360741414649
  },
  {
    "ts": "2025-12-20T18:37:09.296Z",
    "recommendation": "Hold",
    "strength": 0,
    "size_hint": 0.5,
    "reason": "",
    "last_iv": 0.7682564370671837,
    "ema20": 0.7701954361086741,
    "ema100": 0.7675503387538554
  },
  {
    "ts": "2025-12-20T19:23:32.427Z",
    "recommendation": "Hold",
    "strength": 0,
    "size_hint": 0.5,
    "reason": "",
    "last_iv": 0.7684170148282342,
    "ema20": 0.7700260626533941,
    "ema100": 0.7675675006563183
  },
  {
    "ts": "2025-12-20T20:30:12.514Z",
    "recommendation": "Hold",
    "strength": 0,
    "size_hint": 0.5,
    "reason": "",
    "last_iv": 0.7682865860797777,
    "ema20": 0.7698603982178116,
    "ema100": 0.7675817399716343
  },
  {
    "ts": "2025-12-20T21:25:06.124Z",
    "recommendation": "Hold",
    "strength": 0,
    "size_hint": 0.5,
    "reason": "",
    "last_iv": 0.7685773694461621,
    "ema20": 0.769738205001464,
    "ema100": 0.7676014554067734
  },
  {
    "ts": "2025-12-20T22:29:02.886Z",
    "recommendation": "Hold",
    "strength": 0,
    "size_hint": 0.5,
    "reason": "",
    "last_iv": 0.7682433858368242,
    "ema20": 0.7695958412714983,
    "ema100": 0.7676141669004377
  },
  {
    "ts": "2025-12-20T23:26:48.333Z",
    "recommendation": "Hold",
    "strength": 0,
    "size_hint": 0.5,
    "reason": "",
    "last_iv": 0.7682734649191071,
    "ema20": 0.7694699006665086,
    "ema100": 0.767627222306748
  },
  {
    "ts": "2025-12-21T02:27:45.332Z",
    "recommendation": "Long Volatility",
    "strength": 1,
    "size_hint": 1,
    "reason": "EMA20 < EMA100 (bearish IV trend); IV at 10th percentile",
    "last_iv": 0.7362577347939595,
    "ema20": 0.7663068372500753,
    "ema100": 0.7670060443361977
  },
  {
    "ts": "2025-12-21T04:05:18.656Z",
    "recommendation": "Long Volatility",
    "strength": 0.6,
    "size_hint": 0.8,
    "reason": "IV at 10th percentile",
    "last_iv": 0.7355624611394858,
    "ema20": 0.7633788014300192,
    "ema100": 0.7663833991243816
  },
  {
    "ts": "2025-12-21T04:47:18.952Z",
    "recommendation": "Long Volatility",
    "strength": 0.6,
    "size_hint": 0.8,
    "reason": "IV at 10th percentile",
    "last_iv": 0.7354895226985149,
    "ema20": 0.7607226796460664,
    "ema100": 0.7657716391951565
  },
  {
    "ts": "2025-12-21T05:31:42.546Z",
    "recommendation": "Long Volatility",
    "strength": 0.6,
    "size_hint": 0.8,
    "reason": "IV at 10th percentile",
    "last_iv": 0.7353209460416268,
    "ema20": 0.7583034669218341,
    "ema100": 0.7651686551723142
  },
  {
    "ts": "2025-12-21T06:43:38.963Z",
    "recommendation": "Long Volatility",
    "strength": 0.6,
    "size_hint": 0.8,
    "reason": "IV at 10th percentile",
    "last_iv": 0.7353538237281994,
    "ema20": 0.7561177866176785,
    "ema100": 0.7645782624704506
  },
  {
    "ts": "2025-12-21T07:28:22.356Z",
    "recommendation": "Long Volatility",
    "strength": 0.6,
    "size_hint": 0.8,
    "reason": "IV at 10th percentile",
    "last_iv": 0.7353932420413102,
    "ema20": 0.7541440204675481,
    "ema100": 0.7640003412738339
  },
  {
    "ts": "2025-12-21T08:36:36.804Z",
    "recommendation": "Long Volatility",
    "strength": 0.6,
    "size_hint": 0.8,
    "reason": "IV at 10th percentile",
    "last_iv": 0.7352395958940425,
    "ema20": 0.7523435990795952,
    "ema100": 0.763430821563343
  },
  {
    "ts": "2025-12-21T09:29:35.313Z",
    "recommendation": "Long Volatility",
    "strength": 0.6,
    "size_hint": 0.8,
    "reason": "IV at 10th percentile",
    "last_iv": 0.7353252888561382,
    "ema20": 0.7507228076297422,
    "ema100": 0.7628742763612201
  },
  {
    "ts": "2025-12-21T10:31:58.611Z",
    "recommendation": "Long Volatility",
    "strength": 0.6,
    "size_hint": 0.8,
    "reason": "IV at 10th percentile",
    "last_iv": 0.7356843725632384,
    "ema20": 0.7492905757186465,
    "ema100": 0.7623358624246264
  },
  {
    "ts": "2025-12-21T11:24:42.174Z",
    "recommendation": "Long Volatility",
    "strength": 0.6,
    "size_hint": 0.8,
    "reason": "IV at 10th percentile",
    "last_iv": 0.7352786945736305,
    "ema20": 0.7479561108476926,
    "ema100": 0.7618000769226264
  },
  {
    "ts": "2025-12-21T12:55:51.668Z",
    "recommendation": "Long Volatility",
    "strength": 0.6,
    "size_hint": 0.8,
    "reason": "IV at 10th percentile",
    "last_iv": 0.7353562943635852,
    "ema20": 0.7467561283253967,
    "ema100": 0.7612764376640315
  },
  {
    "ts": "2025-12-21T13:34:44.739Z",
    "recommendation": "Long Volatility",
    "strength": 0.6,
    "size_hint": 0.8,
    "reason": "IV at 10th percentile",
    "last_iv": 0.738135237924667,
    "ema20": 0.7459350911443748,
    "ema100": 0.7608181960850342
  },
  {
    "ts": "2025-12-21T14:28:38.442Z",
    "recommendation": "Long Volatility",
    "strength": 0.6,
    "size_hint": 0.8,
    "reason": "IV at 10th percentile",
    "last_iv": 0.7385584048483881,
    "ema20": 0.7452325495923762,
    "ema100": 0.7603774081397541
  },
  {
    "ts": "2025-12-21T15:27:56.040Z",
    "recommendation": "Long Volatility",
    "strength": 0.6,
    "size_hint": 0.8,
    "reason": "IV at 10th percentile",
    "last_iv": 0.7390121477772258,
    "ema20": 0.7446401303718857,
    "ema100": 0.7599543336771298
  },
  {
    "ts": "2025-12-21T16:34:43.784Z",
    "recommendation": "Long Volatility",
    "strength": 0.6,
    "size_hint": 0.8,
    "reason": "IV at 10th percentile",
    "last_iv": 0.7375513843943662,
    "ema20": 0.7439650117073601,
    "ema100": 0.7595107109190553
  },
  {
    "ts": "2025-12-21T17:26:45.513Z",
    "recommendation": "Long Volatility",
    "strength": 0.6,
    "size_hint": 0.8,
    "reason": "IV at 10th percentile",
    "last_iv": 0.7364495391209264,
    "ema20": 0.743249252413414,
    "ema100": 0.7590540540517655
  },
  {
    "ts": "2025-12-21T18:39:15.423Z",
    "recommendation": "Long Volatility",
    "strength": 0.6,
    "size_hint": 0.8,
    "reason": "IV at 10th percentile",
    "last_iv": 0.7379740053498719,
    "ema20": 0.742746847931172,
    "ema100": 0.7586366273447973
  },
  {
    "ts": "2025-12-21T19:23:33.014Z",
    "recommendation": "Long Volatility",
    "strength": 0.6,
    "size_hint": 0.8,
    "reason": "IV at 10th percentile",
    "last_iv": 0.7374215616962594,
    "ema20": 0.7422396778135611,
    "ema100": 0.7582165270349253
  },
  {
    "ts": "2025-12-21T20:31:27.424Z",
    "recommendation": "Long Volatility",
    "strength": 0.6,
    "size_hint": 0.8,
    "reason": "IV at 10th percentile",
    "last_iv": 0.7376623827344457,
    "ema20": 0.7418037449488835,
    "ema100": 0.7578095142764999
  },
  {
    "ts": "2025-12-21T21:26:40.072Z",
    "recommendation": "Long Volatility",
    "strength": 0.6,
    "size_hint": 0.8,
    "reason": "IV at 10th percentile",
    "last_iv": 0.7375920259954054,
    "ema20": 0.741402628858076,
    "ema100": 0.7574091679739039
  },
  {
    "ts": "2025-12-21T22:30:11.750Z",
    "recommendation": "Long Volatility",
    "strength": 0.6,
    "size_hint": 0.8,
    "reason": "IV at 10th percentile",
    "last_iv": 0.7382602572511324,
    "ema20": 0.7411033553717004,
    "ema100": 0.7570299816229579
  },
  {
    "ts": "2025-12-21T23:27:26.510Z",
    "recommendation": "Long Volatility",
    "strength": 0.6,
    "size_hint": 0.8,
    "reason": "IV at 10th percentile",
    "last_iv": 0.7357855028279228,
    "ema20": 0.7405968932246739,
    "ema100": 0.7566092988745413
  },
  {
    "ts": "2025-12-22T02:27:11.026Z",
    "recommendation": "Long Volatility",
    "strength": 0.6,
    "size_hint": 0.8,
    "reason": "IV at 10th percentile",
    "last_iv": 0.736131706305662,
    "ema20": 0.7401716373276251,
    "ema100": 0.7562038019919892
  },
  {
    "ts": "2025-12-22T04:09:42.034Z",
    "recommendation": "Long Volatility",
    "strength": 0.6,
    "size_hint": 0.8,
    "reason": "IV at 10th percentile",
    "last_iv": 0.7366129395766227,
    "ema20": 0.7398327137322915,
    "ema100": 0.755815864122378
  },
  {
    "ts": "2025-12-22T05:35:09.648Z",
    "recommendation": "Long Volatility",
    "strength": 0.6,
    "size_hint": 0.8,
    "reason": "IV at 10th percentile",
    "last_iv": 0.7367718125923777,
    "ema20": 0.739541199338014,
    "ema100": 0.7554387541910909
  }
]