[
  {
    "ts": "2026-03-21T05:52:22.606Z",
    "recommendation": "Hold",
    "strength": 0,
    "size_hint": 0.5,
    "reason": "",
    "last_iv": 0.6867637011812355,
    "ema20": 0.687165943894029,
    "ema100": 0.6804206943552893
  },
  {
    "ts": "2026-03-21T06:59:48.917Z",
    "recommendation": "Hold",
    "strength": 0,
    "size_hint": 0.5,
    "reason": "",
    "last_iv": 0.6867554959168316,
    "ema20": 0.6871268536104864,
    "ema100": 0.6805461359703693
  },
  {
    "ts": "2026-03-21T07:40:58.256Z",
    "recommendation": "Hold",
    "strength": 0,
    "size_hint": 0.5,
    "reason": "",
    "last_iv": 0.6867506477562078,
    "ema20": 0.6870910244815075,
    "ema100": 0.6806689975898907
  },
  {
    "ts": "2026-03-21T08:48:10.642Z",
    "recommendation": "Hold",
    "strength": 0,
    "size_hint": 0.5,
    "reason": "",
    "last_iv": 0.6867717097276346,
    "ema20": 0.6870606135525672,
    "ema100": 0.6807898433747965
  },
  {
    "ts": "2026-03-21T09:43:02.179Z",
    "recommendation": "Hold",
    "strength": 0,
    "size_hint": 0.5,
    "reason": "",
    "last_iv": 0.6867540462725561,
    "ema20": 0.6870314166687567,
    "ema100": 0.6809079464024749
  },
  {
    "ts": "2026-03-21T10:40:43.635Z",
    "recommendation": "Hold",
    "strength": 0,
    "size_hint": 0.5,
    "reason": "",
    "last_iv": 0.6868143951754723,
    "ema20": 0.6870107479551105,
    "ema100": 0.6810249057841183
  },
  {
    "ts": "2026-03-21T11:33:15.746Z",
    "recommendation": "Hold",
    "strength": 0,
    "size_hint": 0.5,
    "reason": "",
    "last_iv": 0.6868350134080673,
    "ema20": 0.6869940113315826,
    "ema100": 0.6811399574202361
  },
  {
    "ts": "2026-03-21T13:10:39.418Z",
    "recommendation": "Hold",
    "strength": 0,
    "size_hint": 0.5,
    "reason": "",
    "last_iv": 0.686865257176263,
    "ema20": 0.6869817490310759,
    "ema100": 0.6812533296926326
  },
  {
    "ts": "2026-03-21T14:39:06.251Z",
    "recommendation": "Hold",
    "strength": 0,
    "size_hint": 0.5,
    "reason": "",
    "last_iv": 0.6867835264910274,
    "ema20": 0.6869628706939285,
    "ema100": 0.6813628385401256
  },
  {
    "ts": "2026-03-21T15:36:51.401Z",
    "recommendation": "Hold",
    "strength": 0,
    "size_hint": 0.5,
    "reason": "",
    "last_iv": 0.6869148935975861,
    "ema20": 0.6869583014466578,
    "ema100": 0.6814727802244317
  },
  {
    "ts": "2026-03-21T16:44:30.280Z",
    "recommendation": "Hold",
    "strength": 0,
    "size_hint": 0.5,
    "reason": "",
    "last_iv": 0.6871007570567067,
    "ema20": 0.6869718686476148,
    "ema100": 0.6815842253102193
  },
  {
    "ts": "2026-03-21T17:36:36.169Z",
    "recommendation": "Hold",
    "strength": 0,
    "size_hint": 0.5,
    "reason": "",
    "last_iv": 0.6871364146621162,
    "ema20": 0.686987539696615,
    "ema100": 0.6816941696538212
  },
  {
    "ts": "2026-03-21T18:52:04.852Z",
    "recommendation": "Hold",
    "strength": 0,
    "size_hint": 0.5,
    "reason": "",
    "last_iv": 0.6870790045023303,
    "ema20": 0.6869962506304926,
    "ema100": 0.681800800046861
  },
  {
    "ts": "2026-03-21T19:34:07.300Z",
    "recommendation": "Hold",
    "strength": 0,
    "size_hint": 0.5,
    "reason": "",
    "last_iv": 0.6873269676289029,
    "ema20": 0.6870277474874841,
    "ema100": 0.6819102291078916
  },
  {
    "ts": "2026-03-21T20:39:11.752Z",
    "recommendation": "Hold",
    "strength": 0,
    "size_hint": 0.5,
    "reason": "",
    "last_iv": 0.6869101172272939,
    "ema20": 0.6870165446055612,
    "ema100": 0.6820092367934242
  },
  {
    "ts": "2026-03-21T21:35:53.677Z",
    "recommendation": "Hold",
    "strength": 0,
    "size_hint": 0.5,
    "reason": "",
    "last_iv": 0.6869173347562343,
    "ema20": 0.6870070960484824,
    "ema100": 0.6821064268520937
  },
  {
    "ts": "2026-03-21T22:38:08.403Z",
    "recommendation": "Hold",
    "strength": 0,
    "size_hint": 0.5,
    "reason": "",
    "last_iv": 0.6870353003330211,
    "ema20": 0.6870097821708194,
    "ema100": 0.6822040283071615
  },
  {
    "ts": "2026-03-21T23:36:06.480Z",
    "recommendation": "Hold",
    "strength": 0,
    "size_hint": 0.5,
    "reason": "",
    "last_iv": 0.6872306003877642,
    "ema20": 0.6870308124771952,
    "ema100": 0.6823035643879655
  },
  {
    "ts": "2026-03-22T03:18:07.991Z",
    "recommendation": "Hold",
    "strength": 0,
    "size_hint": 0.5,
    "reason": "",
    "last_iv": 0.6755237383032792,
    "ema20": 0.685934900651108,
    "ema100": 0.6821693104060905
  },
  {
    "ts": "2026-03-22T05:23:15.915Z",
    "recommendation": "Hold",
    "strength": 0,
    "size_hint": 0.5,
    "reason": "",
    "last_iv": 0.6752251886936296,
    "ema20": 0.6849149280837291,
    "ema100": 0.6820318030454477
  },
  {
    "ts": "2026-03-22T07:04:08.357Z",
    "recommendation": "Hold",
    "strength": 0,
    "size_hint": 0.5,
    "reason": "",
    "last_iv": 0.6755846022429118,
    "ema20": 0.6840263256226989,
    "ema100": 0.6819041357028233
  },
  {
    "ts": "2026-03-22T07:48:05.355Z",
    "recommendation": "Hold",
    "strength": 0,
    "size_hint": 0.5,
    "reason": "",
    "last_iv": 0.6760908111745374,
    "ema20": 0.6832705623419216,
    "ema100": 0.6817890203656295
  },
  {
    "ts": "2026-03-22T08:50:06.336Z",
    "recommendation": "Hold",
    "strength": 0,
    "size_hint": 0.5,
    "reason": "",
    "last_iv": 0.677308312703337,
    "ema20": 0.6827027290430089,
    "ema100": 0.6817002934812276
  },
  {
    "ts": "2026-03-22T09:44:31.552Z",
    "recommendation": "Hold",
    "strength": 0,
    "size_hint": 0.5,
    "reason": "",
    "last_iv": 0.6771181379589334,
    "ema20": 0.6821708632254778,
    "ema100": 0.6816095577283109
  },
  {
    "ts": "2026-03-22T10:41:00.380Z",
    "recommendation": "Hold",
    "strength": 0,
    "size_hint": 0.5,
    "reason": "",
    "last_iv": 0.6784262863331593,
    "ema20": 0.6818142368547808,
    "ema100": 0.6815465226511791
  },
  {
    "ts": "2026-03-22T11:34:08.122Z",
    "recommendation": "Hold",
    "strength": 0,
    "size_hint": 0.5,
    "reason": "",
    "last_iv": 0.6793517517797117,
    "ema20": 0.681579714466679,
    "ema100": 0.6815030618418431
  },
  {
    "ts": "2026-03-22T13:12:32.956Z",
    "recommendation": "Short Volatility",
    "strength": 0.5,
    "size_hint": 0.75,
    "reason": "EMA20 < EMA100 (bearish IV trend)",
    "last_iv": 0.6771921729451134,
    "ema20": 0.6811618533693871,
    "ema100": 0.681417697705274
  },
  {
    "ts": "2026-03-22T14:40:06.871Z",
    "recommendation": "Hold",
    "strength": 0,
    "size_hint": 0.5,
    "reason": "",
    "last_iv": 0.677840389487157,
    "ema20": 0.6808455234758414,
    "ema100": 0.6813468599187767
  },
  {
    "ts": "2026-03-22T15:36:57.343Z",
    "recommendation": "Hold",
    "strength": 0,
    "size_hint": 0.5,
    "reason": "",
    "last_iv": 0.6784700944482133,
    "ema20": 0.6806192921398768,
    "ema100": 0.6812898942658944
  },
  {
    "ts": "2026-03-22T16:44:30.304Z",
    "recommendation": "Hold",
    "strength": 0,
    "size_hint": 0.5,
    "reason": "",
    "last_iv": 0.6786026555005165,
    "ema20": 0.6804272315075568,
    "ema100": 0.6812366816170752
  },
  {
    "ts": "2026-03-22T17:36:29.263Z",
    "recommendation": "Hold",
    "strength": 0,
    "size_hint": 0.5,
    "reason": "",
    "last_iv": 0.678493171292016,
    "ema20": 0.680243035296553,
    "ema100": 0.6811823546799453
  },
  {
    "ts": "2026-03-22T18:53:04.049Z",
    "recommendation": "Hold",
    "strength": 0,
    "size_hint": 0.5,
    "reason": "",
    "last_iv": 0.6797925040311062,
    "ema20": 0.6802001275569867,
    "ema100": 0.6811548328849187
  },
  {
    "ts": "2026-03-22T19:35:52.550Z",
    "recommendation": "Hold",
    "strength": 0,
    "size_hint": 0.5,
    "reason": "",
    "last_iv": 0.6824500523414564,
    "ema20": 0.6804144061078885,
    "ema100": 0.6811804807949492
  },
  {
    "ts": "2026-03-22T20:40:31.080Z",
    "recommendation": "Hold",
    "strength": 0,
    "size_hint": 0.5,
    "reason": "",
    "last_iv": 0.6818620498776666,
    "ema20": 0.6805522769431054,
    "ema100": 0.6811939772124288
  },
  {
    "ts": "2026-03-22T21:36:42.136Z",
    "recommendation": "Hold",
    "strength": 0,
    "size_hint": 0.5,
    "reason": "",
    "last_iv": 0.6866974095519367,
    "ema20": 0.6811375276677559,
    "ema100": 0.6813029560706368
  },
  {
    "ts": "2026-03-22T22:38:41.114Z",
    "recommendation": "Hold",
    "strength": 0,
    "size_hint": 0.5,
    "reason": "",
    "last_iv": 0.681978359330656,
    "ema20": 0.6812176068737463,
    "ema100": 0.6813163303926175
  },
  {
    "ts": "2026-03-22T23:39:05.445Z",
    "recommendation": "Hold",
    "strength": 0,
    "size_hint": 0.5,
    "reason": "",
    "last_iv": 0.6815548278105436,
    "ema20": 0.6812497231534413,
    "ema100": 0.6813210531137646
  },
  {
    "ts": "2026-03-23T03:20:07.418Z",
    "recommendation": "Long Volatility",
    "strength": 0.5,
    "size_hint": 0.75,
    "reason": "EMA20 > EMA100 (bullish IV trend)",
    "last_iv": 0.6829570818386433,
    "ema20": 0.6814123287425082,
    "ema100": 0.6813534497221779
  },
  {
    "ts": "2026-03-23T05:44:56.859Z",
    "recommendation": "Hold",
    "strength": 0,
    "size_hint": 0.5,
    "reason": "",
    "last_iv": 0.6830803683053994,
    "ema20": 0.6815711896532598,
    "ema100": 0.6813876461297664
  },
  {
    "ts": "2026-03-23T07:25:47.312Z",
    "recommendation": "Hold",
    "strength": 0,
    "size_hint": 0.5,
    "reason": "",
    "last_iv": 0.6835458219326773,
    "ema20": 0.6817592498703472,
    "ema100": 0.6814303822842794
  },
  {
    "ts": "2026-03-23T09:10:23.332Z",
    "recommendation": "Hold",
    "strength": 0,
    "size_hint": 0.5,
    "reason": "",
    "last_iv": 0.683186541352399,
    "ema20": 0.6818951823924474,
    "ema100": 0.681465157711371
  },
  {
    "ts": "2026-03-23T11:05:25.630Z",
    "recommendation": "Hold",
    "strength": 0,
    "size_hint": 0.5,
    "reason": "",
    "last_iv": 0.6828114230522899,
    "ema20": 0.6819824434076704,
    "ema100": 0.6814918164309931
  },
  {
    "ts": "2026-03-23T11:53:29.416Z",
    "recommendation": "Short Volatility",
    "strength": 0.6,
    "size_hint": 0.8,
    "reason": "IV at 90th percentile",
    "last_iv": 0.694114018341733,
    "ema20": 0.6831378314966288,
    "ema100": 0.681741761023285
  },
  {
    "ts": "2026-03-23T13:43:21.998Z",
    "recommendation": "Short Volatility",
    "strength": 0.6,
    "size_hint": 0.8,
    "reason": "IV at 90th percentile",
    "last_iv": 0.6977936916685087,
    "ema20": 0.6845336277034745,
    "ema100": 0.6820596210360617
  },
  {
    "ts": "2026-03-23T15:10:16.095Z",
    "recommendation": "Short Volatility",
    "strength": 0.6,
    "size_hint": 0.8,
    "reason": "IV at 90th percentile",
    "last_iv": 0.7177633074946698,
    "ema20": 0.6876983591121597,
    "ema100": 0.6827666247283114
  },
  {
    "ts": "2026-03-23T17:05:33.798Z",
    "recommendation": "Short Volatility",
    "strength": 0.6,
    "size_hint": 0.8,
    "reason": "IV at 90th percentile",
    "last_iv": 0.6977428320464053,
    "ema20": 0.6886549755820879,
    "ema100": 0.6830631832890657
  },
  {
    "ts": "2026-03-23T18:01:50.109Z",
    "recommendation": "Short Volatility",
    "strength": 0.6,
    "size_hint": 0.8,
    "reason": "IV at 90th percentile",
    "last_iv": 0.7026621061196459,
    "ema20": 0.6899889880142362,
    "ema100": 0.6834512807708594
  },
  {
    "ts": "2026-03-23T19:10:00.513Z",
    "recommendation": "Short Volatility",
    "strength": 0.6,
    "size_hint": 0.8,
    "reason": "IV at 90th percentile",
    "last_iv": 0.7081844444765873,
    "ema20": 0.6917218886296983,
    "ema100": 0.6839410463887945
  },
  {
    "ts": "2026-03-23T20:50:36.253Z",
    "recommendation": "Short Volatility",
    "strength": 0.6,
    "size_hint": 0.8,
    "reason": "IV at 90th percentile",
    "last_iv": 0.7072564096520756,
    "ema20": 0.6932013668223057,
    "ema100": 0.6844027367504436
  },
  {
    "ts": "2026-03-23T21:48:26.190Z",
    "recommendation": "Short Volatility",
    "strength": 0.6,
    "size_hint": 0.8,
    "reason": "IV at 90th percentile",
    "last_iv": 0.7063217651009366,
    "ema20": 0.6944509285631276,
    "ema100": 0.6848367769157999
  }
]