{
  "assets": [
    {
      "symbol": "BTC",
      "files": {
        "smile": "/BTC/cvi.json",
        "smile_meta": "/BTC/smile_meta.json",
        "series": "/BTC/cvi_timeseries.json",
        "signals": "/BTC/signals.json"
      },
      "latest": {
        "t": "2026-04-26T15:53:43.346Z",
        "spot": 78064,
        "days_to_expiry": "32.67",
        "atm_iv": 0.01,
        "vega_weighted_iv": 0.010282811662972017
      }
    },
    {
      "symbol": "ETH",
      "files": {
        "smile": "/ETH/cvi.json",
        "smile_meta": "/ETH/smile_meta.json",
        "series": "/ETH/cvi_timeseries.json",
        "signals": "/ETH/signals.json"
      },
      "latest": {
        "t": "2026-04-26T15:53:51.077Z",
        "spot": 2345.97,
        "days_to_expiry": "32.67",
        "atm_iv": 0.029827204416776578,
        "vega_weighted_iv": 0.05236973853295484
      }
    },
    {
      "symbol": "LINK",
      "files": {
        "smile": "/LINK/cvi.json",
        "smile_meta": "/LINK/smile_meta.json",
        "series": "/LINK/cvi_timeseries.json",
        "signals": "/LINK/signals.json"
      },
      "latest": {
        "t": "2026-04-26T15:53:56.040Z",
        "spot": 9.48,
        "days_to_expiry": "30.00",
        "atm_iv": 0.5137332800542815,
        "vega_weighted_iv": 0.5137332800542815
      }
    }
  ]
}