{
  "assets": [
    {
      "symbol": "BTC",
      "files": {
        "smile": "/BTC/cvi.json",
        "smile_meta": "/BTC/smile_meta.json",
        "series": "/BTC/cvi_timeseries.json",
        "signals": "/BTC/signals.json"
      },
      "latest": {
        "t": "2026-01-13T13:06:37.388Z",
        "spot": 91912,
        "days_to_expiry": "16.79",
        "atm_iv": 0.014523772943836383,
        "vega_weighted_iv": 0.031983812209138915
      }
    },
    {
      "symbol": "ETH",
      "files": {
        "smile": "/ETH/cvi.json",
        "smile_meta": "/ETH/smile_meta.json",
        "series": "/ETH/cvi_timeseries.json",
        "signals": "/ETH/signals.json"
      },
      "latest": {
        "t": "2026-01-13T13:06:45.219Z",
        "spot": 3128.54,
        "days_to_expiry": "16.79",
        "atm_iv": 0.019407876759996837,
        "vega_weighted_iv": 0.043262478183153215
      }
    },
    {
      "symbol": "LINK",
      "files": {
        "smile": "/LINK/cvi.json",
        "smile_meta": "/LINK/smile_meta.json",
        "series": "/LINK/cvi_timeseries.json",
        "signals": "/LINK/signals.json"
      },
      "latest": {
        "t": "2026-01-13T13:06:50.951Z",
        "spot": 13.26,
        "days_to_expiry": "30.00",
        "atm_iv": 0.46095153296401514,
        "vega_weighted_iv": 0.46095153296401514
      }
    }
  ]
}