{
  "assets": [
    {
      "symbol": "BTC",
      "files": {
        "smile": "/BTC/cvi.json",
        "smile_meta": "/BTC/smile_meta.json",
        "series": "/BTC/cvi_timeseries.json",
        "signals": "/BTC/signals.json"
      },
      "latest": {
        "t": "2025-11-09T10:27:43.142Z",
        "spot": 101689,
        "days_to_expiry": "18.90",
        "atm_iv": 0.01,
        "vega_weighted_iv": 0.02401682075208896
      }
    },
    {
      "symbol": "ETH",
      "files": {
        "smile": "/ETH/cvi.json",
        "smile_meta": "/ETH/smile_meta.json",
        "series": "/ETH/cvi_timeseries.json",
        "signals": "/ETH/signals.json"
      },
      "latest": {
        "t": "2025-11-09T10:27:49.959Z",
        "spot": 3390.03,
        "days_to_expiry": "18.90",
        "atm_iv": 0.023747661496208064,
        "vega_weighted_iv": 0.04454901185815641
      }
    },
    {
      "symbol": "LINK",
      "files": {
        "smile": "/LINK/cvi.json",
        "smile_meta": "/LINK/smile_meta.json",
        "series": "/LINK/cvi_timeseries.json",
        "signals": "/LINK/signals.json"
      },
      "latest": {
        "t": "2025-11-09T10:27:54.821Z",
        "spot": 15.12,
        "days_to_expiry": "30.00",
        "atm_iv": 0.9155789450513009,
        "vega_weighted_iv": 0.9155789450513009
      }
    }
  ]
}