{
  "assets": [
    {
      "symbol": "BTC",
      "files": {
        "smile": "/BTC/cvi.json",
        "smile_meta": "/BTC/smile_meta.json",
        "series": "/BTC/cvi_timeseries.json",
        "signals": "/BTC/signals.json"
      },
      "latest": {
        "t": "2026-01-05T13:06:03.530Z",
        "spot": 92828,
        "days_to_expiry": "24.79",
        "atm_iv": 0.011444131053358467,
        "vega_weighted_iv": 0.02875251615546478
      }
    },
    {
      "symbol": "ETH",
      "files": {
        "smile": "/ETH/cvi.json",
        "smile_meta": "/ETH/smile_meta.json",
        "series": "/ETH/cvi_timeseries.json",
        "signals": "/ETH/signals.json"
      },
      "latest": {
        "t": "2026-01-05T13:06:10.348Z",
        "spot": 3169.37,
        "days_to_expiry": "24.79",
        "atm_iv": 0.03511049684772972,
        "vega_weighted_iv": 0.055967504737117736
      }
    },
    {
      "symbol": "LINK",
      "files": {
        "smile": "/LINK/cvi.json",
        "smile_meta": "/LINK/smile_meta.json",
        "series": "/LINK/cvi_timeseries.json",
        "signals": "/LINK/signals.json"
      },
      "latest": {
        "t": "2026-01-05T13:06:15.628Z",
        "spot": 13.55,
        "days_to_expiry": "30.00",
        "atm_iv": 0.4779171035330301,
        "vega_weighted_iv": 0.4779171035330301
      }
    }
  ]
}