{
  "assets": [
    {
      "symbol": "BTC",
      "files": {
        "smile": "/BTC/cvi.json",
        "smile_meta": "/BTC/smile_meta.json",
        "series": "/BTC/cvi_timeseries.json",
        "signals": "/BTC/signals.json"
      },
      "latest": {
        "t": "2026-02-17T10:02:17.107Z",
        "spot": 68083,
        "days_to_expiry": "37.92",
        "atm_iv": 0.01,
        "vega_weighted_iv": 0.010304463037634074
      }
    },
    {
      "symbol": "ETH",
      "files": {
        "smile": "/ETH/cvi.json",
        "smile_meta": "/ETH/smile_meta.json",
        "series": "/ETH/cvi_timeseries.json",
        "signals": "/ETH/signals.json"
      },
      "latest": {
        "t": "2026-02-17T10:02:22.810Z",
        "spot": 1974.56,
        "days_to_expiry": "37.92",
        "atm_iv": 0.050397277585188596,
        "vega_weighted_iv": 0.06624954691887631
      }
    },
    {
      "symbol": "LINK",
      "files": {
        "smile": "/LINK/cvi.json",
        "smile_meta": "/LINK/smile_meta.json",
        "series": "/LINK/cvi_timeseries.json",
        "signals": "/LINK/signals.json"
      },
      "latest": {
        "t": "2026-02-17T10:02:27.012Z",
        "spot": 8.81,
        "days_to_expiry": "30.00",
        "atm_iv": 0.9048065377134765,
        "vega_weighted_iv": 0.9048065377134765
      }
    }
  ]
}