{
  "assets": [
    {
      "symbol": "BTC",
      "files": {
        "smile": "/BTC/cvi.json",
        "smile_meta": "/BTC/smile_meta.json",
        "series": "/BTC/cvi_timeseries.json",
        "signals": "/BTC/signals.json"
      },
      "latest": {
        "t": "2025-09-30T01:56:12.626Z",
        "spot": 114354,
        "days_to_expiry": "31.25",
        "atm_iv": 0.01,
        "vega_weighted_iv": 0.010286924966433521
      }
    },
    {
      "symbol": "ETH",
      "files": {
        "smile": "/ETH/cvi.json",
        "smile_meta": "/ETH/smile_meta.json",
        "series": "/ETH/cvi_timeseries.json",
        "signals": "/ETH/signals.json"
      },
      "latest": {
        "t": "2025-09-30T01:56:20.864Z",
        "spot": 4195.65,
        "days_to_expiry": "31.25",
        "atm_iv": 0.01,
        "vega_weighted_iv": 0.013293370055518006
      }
    },
    {
      "symbol": "LINK",
      "files": {
        "smile": "/LINK/cvi.json",
        "smile_meta": "/LINK/smile_meta.json",
        "series": "/LINK/cvi_timeseries.json",
        "signals": "/LINK/signals.json"
      },
      "latest": {
        "t": "2025-09-30T01:56:27.784Z",
        "spot": 21.56,
        "days_to_expiry": "30.00",
        "atm_iv": 0.5776940268779279,
        "vega_weighted_iv": 0.5776940268779279
      }
    }
  ]
}