{
  "assets": [
    {
      "symbol": "BTC",
      "files": {
        "smile": "/BTC/cvi.json",
        "smile_meta": "/BTC/smile_meta.json",
        "series": "/BTC/cvi_timeseries.json",
        "signals": "/BTC/signals.json"
      },
      "latest": {
        "t": "2026-01-01T06:48:16.473Z",
        "spot": 87524,
        "days_to_expiry": "29.05",
        "atm_iv": 0.019118865951404145,
        "vega_weighted_iv": 0.03282244236803896
      }
    },
    {
      "symbol": "ETH",
      "files": {
        "smile": "/ETH/cvi.json",
        "smile_meta": "/ETH/smile_meta.json",
        "series": "/ETH/cvi_timeseries.json",
        "signals": "/ETH/signals.json"
      },
      "latest": {
        "t": "2026-01-01T06:48:22.372Z",
        "spot": 2973.53,
        "days_to_expiry": "29.05",
        "atm_iv": 0.036574324557459445,
        "vega_weighted_iv": 0.05741763100836726
      }
    },
    {
      "symbol": "LINK",
      "files": {
        "smile": "/LINK/cvi.json",
        "smile_meta": "/LINK/smile_meta.json",
        "series": "/LINK/cvi_timeseries.json",
        "signals": "/LINK/signals.json"
      },
      "latest": {
        "t": "2026-01-01T06:48:26.242Z",
        "spot": 12.22,
        "days_to_expiry": "30.00",
        "atm_iv": 0.5504488093893687,
        "vega_weighted_iv": 0.5504488093893687
      }
    }
  ]
}