{
  "assets": [
    {
      "symbol": "BTC",
      "files": {
        "smile": "/BTC/cvi.json",
        "series": "/BTC/cvi_timeseries.json",
        "signals": "/BTC/signals.json"
      },
      "latest": {
        "t": "2025-09-01T01:52:25.285Z",
        "spot": 108219,
        "days_to_expiry": "25.26",
        "atm_iv": 0.017289124058803815,
        "vega_weighted_iv": 0.03453066606179212
      }
    },
    {
      "symbol": "ETH",
      "files": {
        "smile": "/ETH/cvi.json",
        "series": "/ETH/cvi_timeseries.json",
        "signals": "/ETH/signals.json"
      },
      "latest": {
        "t": "2025-09-01T01:52:25.847Z",
        "spot": 4418.1,
        "days_to_expiry": "25.26",
        "atm_iv": 0.027451117967082966,
        "vega_weighted_iv": 0.05085459211574632
      }
    },
    {
      "symbol": "SOL",
      "files": {
        "smile": "/SOL/cvi.json",
        "series": "/SOL/cvi_timeseries.json",
        "signals": "/SOL/signals.json"
      },
      "latest": {
        "t": "2025-09-01T01:52:26.043Z",
        "spot": 201.64,
        "days_to_expiry": "30.00",
        "atm_iv": 0.8523818973077089,
        "vega_weighted_iv": 0.8523818973077089
      }
    },
    {
      "symbol": "BNB",
      "files": {
        "smile": "/BNB/cvi.json",
        "series": "/BNB/cvi_timeseries.json",
        "signals": "/BNB/signals.json"
      },
      "latest": {
        "t": "2025-09-01T01:52:26.416Z",
        "spot": 863.96,
        "days_to_expiry": null,
        "atm_iv": null,
        "vega_weighted_iv": null
      }
    }
  ]
}