{
  "assets": [
    {
      "symbol": "BTC",
      "files": {
        "smile": "/BTC/cvi.json",
        "smile_meta": "/BTC/smile_meta.json",
        "series": "/BTC/cvi_timeseries.json",
        "signals": "/BTC/signals.json"
      },
      "latest": {
        "t": "2026-05-18T14:37:04.098Z",
        "spot": 76337,
        "days_to_expiry": "38.72",
        "atm_iv": 0.01,
        "vega_weighted_iv": 0.010593216850294074
      }
    },
    {
      "symbol": "ETH",
      "files": {
        "smile": "/ETH/cvi.json",
        "smile_meta": "/ETH/smile_meta.json",
        "series": "/ETH/cvi_timeseries.json",
        "signals": "/ETH/signals.json"
      },
      "latest": {
        "t": "2026-05-18T14:37:09.212Z",
        "spot": 2105.75,
        "days_to_expiry": "38.72",
        "atm_iv": 0.01,
        "vega_weighted_iv": 0.015255320716524084
      }
    },
    {
      "symbol": "LINK",
      "files": {
        "smile": "/LINK/cvi.json",
        "smile_meta": "/LINK/smile_meta.json",
        "series": "/LINK/cvi_timeseries.json",
        "signals": "/LINK/signals.json"
      },
      "latest": {
        "t": "2026-05-18T14:37:12.735Z",
        "spot": 9.41,
        "days_to_expiry": "30.00",
        "atm_iv": 0.41399702596435,
        "vega_weighted_iv": 0.41399702596435
      }
    }
  ]
}