[
  {
    "symbol": "BTC",
    "ts": "2026-01-14T09:39:32Z",
    "horizon_days": 1,
    "features": [
      "iv",
      "rv7",
      "rv30",
      "mom7",
      "mom30",
      "rsi14",
      "iv_minus_rv30"
    ],
    "sample_size": 364,
    "predicted_return": 0.0028175737617152775,
    "next_day_return_pred": 0.0028175737617152775,
    "prob_up": 0.5194743921299348,
    "rmse": 0.021611507711072574,
    "auc": 0.47925191247109056,
    "model": "histgb",
    "for_date": "2026-01-14"
  },
  {
    "symbol": "ETH",
    "ts": "2026-01-14T09:39:33Z",
    "horizon_days": 1,
    "features": [
      "iv",
      "rv7",
      "rv30",
      "mom7",
      "mom30",
      "rsi14",
      "iv_minus_rv30"
    ],
    "sample_size": 364,
    "predicted_return": -0.010242694470676767,
    "next_day_return_pred": -0.010242694470676767,
    "prob_up": 0.7213326539820046,
    "rmse": 0.04236671954456238,
    "auc": 0.49781600998395437,
    "model": "histgb",
    "for_date": "2026-01-14"
  },
  {
    "symbol": "LINK",
    "ts": "2026-01-14T09:39:34Z",
    "horizon_days": 1,
    "features": [
      "iv",
      "rv7",
      "rv30",
      "mom7",
      "mom30",
      "rsi14",
      "iv_minus_rv30"
    ],
    "sample_size": 364,
    "predicted_return": -0.009434669405136802,
    "next_day_return_pred": -0.009434669405136802,
    "prob_up": 0.5171802095514918,
    "rmse": 0.04698771504738202,
    "auc": 0.4828636201991465,
    "model": "histgb",
    "for_date": "2026-01-14"
  }
]